HISTORY.txt
LICENSE.txt
MANIFEST.in
README.md
setup.cfg
setup.py
sparc/__init__.py
sparc.proxy.egg-info/PKG-INFO
sparc.proxy.egg-info/SOURCES.txt
sparc.proxy.egg-info/dependency_links.txt
sparc.proxy.egg-info/entry_points.txt
sparc.proxy.egg-info/namespace_packages.txt
sparc.proxy.egg-info/not-zip-safe
sparc.proxy.egg-info/requires.txt
sparc.proxy.egg-info/top_level.txt
sparc/proxy/__init__.py
sparc/proxy/configure.zcml
sparc/proxy/ftesting.zcml
sparc/proxy/interface.py
sparc/proxy/interfaces.py
sparc/proxy/testing.py
sparc/proxy/tests/__init__.py
sparc/proxy/tests/test_interface.py